qudit/__init__.py
qudit/index.py
qudit/random.py
qudit/utils.py
qudit/algo/__init__.py
qudit/algo/qaoa.py
qudit/algo/statiliser.py
qudit/circuit/__init__.py
qudit/circuit/gates.py
qudit/circuit/index.py
qudit/circuit/transform.py
qudit/ml/__init__.py
qudit/ml/index.py
qudit/noise/__init__.py
qudit/noise/index.py
qudit/noise/kraus.py
qudit/noise/lib.py
qudit/noise/recovery.py
qudit/tools/__init__.py
qudit/tools/entanglement.py
qudit/tools/metrics.py
qudit/tools/states.py
qudit/tools/tests.py
qudit-0.2.2.dist-info/METADATA
qudit-0.2.2.dist-info/WHEEL
qudit-0.2.2.dist-info/top_level.txt
qudit-0.2.2.dist-info/RECORD
