Metadata-Version: 2.4
Name: qudit
Version: 0.2.2
Summary: High performance quantum sims on qudits
Home-page: https://github.com/plutoniumm/qudit
Author: plutoniumm
License: MIT
Requires-Python: >=3.11
Requires-Dist: numpy
Requires-Dist: torch
Provides-Extra: dev
Requires-Dist: pytest; extra == "dev"
Requires-Dist: twine; extra == "dev"
Requires-Dist: wheel; extra == "dev"
Dynamic: author
Dynamic: description
Dynamic: description-content-type
Dynamic: home-page
Dynamic: license
Dynamic: provides-extra
Dynamic: requires-dist
Dynamic: requires-python
Dynamic: summary
